[["Map",1,2,9,10,31,32],"meta::meta",["Map",3,4,5,6,7,8],"astro-version","5.13.10","content-config-digest","f6123819eadf773a","astro-config-digest","{\"root\":{},\"srcDir\":{},\"publicDir\":{},\"outDir\":{},\"cacheDir\":{},\"site\":\"https://fuwari.vercel.app/\",\"compressHTML\":true,\"base\":\"/\",\"trailingSlash\":\"always\",\"output\":\"static\",\"scopedStyleStrategy\":\"attribute\",\"build\":{\"format\":\"directory\",\"client\":{},\"server\":{},\"assets\":\"_astro\",\"serverEntry\":\"entry.mjs\",\"redirects\":true,\"inlineStylesheets\":\"auto\",\"concurrency\":1},\"server\":{\"open\":false,\"host\":false,\"port\":4321,\"streaming\":true,\"allowedHosts\":[]},\"redirects\":{},\"image\":{\"endpoint\":{\"route\":\"/_image/\"},\"service\":{\"entrypoint\":\"astro/assets/services/sharp\",\"config\":{}},\"domains\":[],\"remotePatterns\":[],\"responsiveStyles\":false},\"devToolbar\":{\"enabled\":true},\"markdown\":{\"syntaxHighlight\":false,\"shikiConfig\":{\"langs\":[],\"langAlias\":{},\"theme\":\"github-dark\",\"themes\":{},\"wrap\":false,\"transformers\":[]},\"remarkPlugins\":[null,null,null,null,null,null,null],\"rehypePlugins\":[null,null,[null,{\"components\":{}}],[null,{\"behavior\":\"append\",\"properties\":{\"className\":[\"anchor\"]},\"content\":{\"type\":\"element\",\"tagName\":\"span\",\"properties\":{\"className\":[\"anchor-icon\"],\"data-pagefind-ignore\":true},\"children\":[{\"type\":\"text\",\"value\":\"#\"}]}}],[null,{\"themes\":[\"github-dark\",\"github-dark\"],\"plugins\":[{\"name\":\"Collapsible sections\",\"styleSettings\":{\"defaultValues\":{\"collapsibleSections\":{\"closedBorderWidth\":\"0\",\"closedPaddingBlock\":\"4px\",\"closedMargin\":\"0\",\"closedFontFamily\":\"inherit\",\"closedFontSize\":\"inherit\",\"closedLineHeight\":\"inherit\",\"openBorderWidth\":\"1px\",\"openPadding\":\"0\",\"openMargin\":\"0\",\"openBackgroundColor\":\"transparent\",\"openBorderColor\":\"transparent\",\"expandIcon\":\"url(\\\"data:image/svg+xml,%3Csvg%20xmlns%3D'http%3A%2F%2Fwww.w3.org%2F2000%2Fsvg'%20viewBox%3D'0%200%2016%2016'%3E%3Cpath%20d%3D'm8.177.677%202.896%202.896a.25.25%200%200%201-.177.427H8.75v1.25a.75.75%200%200%201-1.5%200V4H5.104a.25.25%200%200%201-.177-.427L7.823.677a.25.25%200%200%201%20.354%200ZM7.25%2010.75a.75.75%200%200%201%201.5%200V12h2.146a.25.25%200%200%201%20.177.427l-2.896%202.896a.25.25%200%200%201-.354%200l-2.896-2.896A.25.25%200%200%201%205.104%2012H7.25v-1.25Zm-5-2a.75.75%200%200%200%200-1.5h-.5a.75.75%200%200%200%200%201.5h.5ZM6%208a.75.75%200%200%201-.75.75h-.5a.75.75%200%200%201%200-1.5h.5A.75.75%200%200%201%206%208Zm2.25.75a.75.75%200%200%200%200-1.5h-.5a.75.75%200%200%200%200%201.5h.5ZM12%208a.75.75%200%200%201-.75.75h-.5a.75.75%200%200%201%200-1.5h.5A.75.75%200%200%201%2012%208Zm2.25.75a.75.75%200%200%200%200-1.5h-.5a.75.75%200%200%200%200%201.5h.5Z'%2F%3E%3C%2Fsvg%3E\\\")\",\"collapseIcon\":\"url(\\\"data:image/svg+xml,%3Csvg%20xmlns%3D'http%3A%2F%2Fwww.w3.org%2F2000%2Fsvg'%20viewBox%3D'0%200%2016%2016'%3E%3Cpath%20d%3D'M10.896%202H8.75V.75a.75.75%200%200%200-1.5%200V2H5.104a.25.25%200%200%200-.177.427l2.896%202.896a.25.25%200%200%200%20.354%200l2.896-2.896A.25.25%200%200%200%2010.896%202ZM8.75%2015.25a.75.75%200%200%201-1.5%200V14H5.104a.25.25%200%200%201-.177-.427l2.896-2.896a.25.25%200%200%201%20.354%200l2.896%202.896a.25.25%200%200%201-.177.427H8.75v1.25Zm-6.5-6.5a.75.75%200%200%200%200-1.5h-.5a.75.75%200%200%200%200%201.5h.5ZM6%208a.75.75%200%200%201-.75.75h-.5a.75.75%200%200%201%200-1.5h.5A.75.75%200%200%201%206%208Zm2.25.75a.75.75%200%200%200%200-1.5h-.5a.75.75%200%200%200%200%201.5h.5ZM12%208a.75.75%200%200%201-.75.75h-.5a.75.75%200%200%201%200-1.5h.5A.75.75%200%200%201%2012%208Zm2.25.75a.75.75%200%200%200%200-1.5h-.5a.75.75%200%200%200%200%201.5h.5Z'%2F%3E%3C%2Fsvg%3E\\\")\"}},\"cssVarExclusions\":[],\"cssVarReplacements\":[[\"collapsibleSections\",\"cs\"]],\"preventUnitlessValues\":[\"collapsibleSections.closedBorderWidth\",\"collapsibleSections.openBorderWidth\"]},\"hooks\":{}},{\"name\":\"Line numbers\",\"styleSettings\":{\"defaultValues\":{\"lineNumbers\":{\"foreground\":\"inherit\",\"highlightForeground\":\"inherit\"}},\"cssVarExclusions\":[],\"cssVarReplacements\":[],\"preventUnitlessValues\":[]},\"hooks\":{}},{\"name\":\"Language Badge\"},{\"name\":\"Custom Copy Button\",\"hooks\":{}},{\"name\":\"astro-expressive-code\",\"hooks\":{}}],\"defaultProps\":{\"wrap\":true,\"overridesByLang\":{\"shellsession\":{\"showLineNumbers\":false}}},\"styleOverrides\":{\"codeBackground\":\"var(--codeblock-bg)\",\"borderRadius\":\"0.75rem\",\"borderColor\":\"none\",\"codeFontSize\":\"0.875rem\",\"codeFontFamily\":\"'JetBrains Mono Variable', ui-monospace, SFMono-Regular, Menlo, Monaco, Consolas, 'Liberation Mono', 'Courier New', monospace\",\"codeLineHeight\":\"1.5rem\",\"frames\":{\"editorBackground\":\"var(--codeblock-bg)\",\"terminalBackground\":\"var(--codeblock-bg)\",\"terminalTitlebarBackground\":\"var(--codeblock-topbar-bg)\",\"editorTabBarBackground\":\"var(--codeblock-topbar-bg)\",\"editorActiveTabBackground\":\"none\",\"editorActiveTabIndicatorBottomColor\":\"var(--primary)\",\"editorActiveTabIndicatorTopColor\":\"none\",\"editorTabBarBorderBottomColor\":\"var(--codeblock-topbar-bg)\",\"terminalTitlebarBorderBottomColor\":\"none\"},\"textMarkers\":{\"delHue\":0,\"insHue\":180,\"markHue\":250}},\"frames\":{\"showCopyToClipboardButton\":false}}]],\"remarkRehype\":{},\"gfm\":true,\"smartypants\":true},\"security\":{\"checkOrigin\":true},\"env\":{\"schema\":{},\"validateSecrets\":false},\"experimental\":{\"clientPrerender\":false,\"contentIntellisense\":false,\"headingIdCompat\":false,\"preserveScriptOrder\":false,\"liveContentCollections\":false,\"csp\":false,\"staticImportMetaEnv\":false,\"chromeDevtoolsWorkspace\":false},\"legacy\":{\"collections\":false}}","spec",["Map",11,12],"about",{"id":11,"data":13,"body":14,"filePath":15,"digest":16,"rendered":17,"legacyId":30},{},"# About\n学术经历：\n香港科技大学-本科","src/content/spec/about.md","47e1f3d7163f32d5",{"html":18,"metadata":19},"\u003Csection>\u003Ch1 id=\"about\">About\u003Ca class=\"anchor\" href=\"#about\">\u003Cspan class=\"anchor-icon\" data-pagefind-ignore=\"\">#\u003C/span>\u003C/a>\u003C/h1>\u003Cp>学术经历：\n香港科技大学-本科\u003C/p>\u003C/section>",{"headings":20,"localImagePaths":24,"remoteImagePaths":25,"frontmatter":26,"imagePaths":29},[21],{"depth":22,"slug":11,"text":23},1,"About#",[],[],{"minutes":22,"words":27,"excerpt":28},13,"学术经历：\n香港科技大学-本科",[],"about.md","posts",["Map",33,34],"usingslurm/usingslurm",{"id":33,"data":35,"body":45,"filePath":46,"digest":47,"rendered":48,"legacyId":145},{"title":36,"published":37,"draft":38,"description":39,"image":40,"tags":41,"category":44,"lang":40,"prevTitle":40,"prevSlug":40,"nextTitle":40,"nextSlug":40},"使用我们的Slurm集群",["Date","2026-03-01T00:00:00.000Z"],false,"本篇文章主要介绍了怎么使用我们内部的slurm集群","",[42,43],"教程","Slurm","Guides","# Slurm集群使用指南\n\n欢迎使用本集群。本文档将引导您完成从环境配置到作业提交的完整流程，帮助您高效利用计算资源。\n\n---\n\n## 0. 系统架构\n\n集群由六台服务器组成，通过一台 **40G 以太网交换机**互连，构建高速计算网络。\n\n\u003C!-- ```mermaid\ngraph TD\n    Switch[Mellanox SX6012 40G 交换机]\n\n    Login[登录服务器]\n    GPU[\"GPU服务器\u003Cbr/>64c128t | 120GB RAM\u003Cbr/>8×NVIDIA 4090 48GB\"]\n    CPU1[\"CPU服务器1\u003Cbr/>48c96t | 128GB RAM\"]\n    CPU2[\"CPU服务器2\u003Cbr/>48c96t | 256GB RAM\"]\n    Storage[\"存储服务器\u003Cbr/>48TB 阵列\u003Cbr/>1TB NVMe SSD 缓存\u003Cbr/>256GB Optane PMEM\"]\n\n    Login --- Switch\n    GPU --- Switch\n    CPU1 --- Switch\n    CPU2 --- Switch\n    Storage --- Switch\n``` \n-->\n\n\n**硬件配置明细**：\n\n- **控制服务器**：控制节点，用于作业调度、提供REST API。\n- **登录服务器**：用户接入节点，用于作业提交和管理。\n- **GPU服务器**：64核心128线程，120GB内存，8张NVIDIA 4090 48GB显卡。\n- **CPU服务器1**：48核心96线程，128GB内存。\n- **CPU服务器2**：48核心96线程，256GB内存。\n- **存储服务器**：48TB硬盘阵列，配备1TB NVMe SSD高速缓存和256GB Intel Optane PMEM超高速缓存。\n\n\u003Cimg width=\"1512\" height=\"867\" alt=\"零信任平台入口\" src=\"/posts/usingSlurm/topology.png\" />\n\n注意：控制节点和登陆节点是一台mac mini上跑的虚拟机。因此，对于登陆节点，请不要再上面编译程序或者运行代码，基本上编不出来，编出来了你在计算节点上也跑不了~~你要交叉编译那我也没啥好说的~~。\n\n---\n\n## 1. 环境与基本配置\n\n出于安全因素，除SSH，所有的敏感业务访问都必须通过 `Cloudflare 零信任平台` 进行登录，Cloudflare会记录你的用户态，单次有效期最长为24小时。你的密码修改，证书获取，以及查看我们的web面板，都属于敏感业务。\n\n### 1.1 登录零信任平台\n访问 [https://ai4qc-hkust.cloudflareaccess.com/](https://ai4qc-hkust.cloudflareaccess.com/)。  \n**注意**：必须使用已在 `ai4qc` 组织内的 GitHub 帐户登录，否则无法获得授权。  \n成功登录后，您将看到如下界面：  \n\u003Cimg width=\"1512\" height=\"867\" alt=\"零信任平台入口\" src=\"/posts/usingSlurm/zt-entrypoint.png\" />\n\n\n\n### 1.2 访问用户管理界面\n点击零信任平台中的 **profile** 或直接访问 [https://profile.ai4qc.icu/](https://profile.ai4qc.icu/) 进入用户管理界面。  \n\u003Cimg width=\"1512\" height=\"867\" alt=\"image\" src=\"/posts/usingSlurm/go-ldap-login.png\" />\n\n\n### 1.3 首次登录与初始密码\n- 点击 **OAuth 登录**，使用您的 GitHub 账号授权。初次登录将自动完成用户注册。\n- 登录成功后进入个人主页。**新用户会弹出初始密码**，请妥善保存；您可以立即修改或暂时忽略。  \n\u003Cimg width=\"1512\" height=\"867\" alt=\"image\" src=\"/posts/usingSlurm/profile-page.png\" />\n\n\n### 1.4 获取 SSH 证书\n在个人主页中，找到 **“生成并下载 SSH 证书”** 区域，点击 **“生成”** 按钮。系统将生成一对证书并自动下载为一个压缩包：\n- **私钥文件**：文件名格式为 `[用户名]-[日期]`（例如 `zhangsan-20250302`）\n- **签名证书**：文件名格式为 `[用户名]-[日期]-cert.crt`（例如 `zhangsan-20250302-cert.crt`）\n\n解压后，您可以选择以下任一方式使用证书连接集群：\n\n#### 1.4.0 注意事项\n```bash\n以防有人不仔细看，SSH 记得加端口9922\n```\n\n\n#### 1.4.1 使用命令行直接登录\n```bash\nssh -i /path/to/private_key_file \u003Cusername>@login.ai4qc.icu -p 9922\n```\n（SSH 客户端会自动寻找同名的证书文件，无需额外指定。）\n\n#### 1.4.2 配置 SSH config\n在 `~/.ssh/config` 中添加如下配置：\n```bash\nHost ai4qc\n    HostName login.ai4qc.icu\n    User \u003Cyour-username>\n    Port 9922\n    IdentityFile /path/to/private_key_file\n    CertificateFile /path/to/cert_file\n```\n之后可直接使用 `ssh ai4qc` 登录。\n\n#### 1.4.3 在 VS Code 中使用\n参考官方文档 [Improving your security with a dedicated key](https://code.visualstudio.com/docs/remote/troubleshooting#_improving-your-security-with-a-dedicated-key)，配置 Remote-SSH 使用证书。\n\n#### 1.4.4 在 Termius 中使用\nTermius 支持直接导入 SSH 证书，请参阅 [Import SSH Certificate](https://termius.com/documentation/ssh-certificates) 完成设置。\n\n### 1.5 配置终端（可选）\n默认登录 Shell 为 **zsh**，其具备强大的自动补全和主题功能。如需切换为 bash，请在登录后进入 **“终端设置”** → **“Shell”** 进行修改。\n\n### 1.6 连接集群\n完成上述配置后，即可通过 SSH 正常登录集群：\n```bash\nssh \u003Cusername>@login.ai4qc.icu -p 9922\n```\n\n---\n\n## 2. Slurm 作业调度系统使用\n\n一些基本说明\n\n### 2.1 分区说明\n集群包含两个分区（Partition）：\n- **cpu**：用于纯 CPU 计算任务（默认分区）。\n- **gpu**：用于 GPU 加速任务。\n\n提交作业时若未指定分区，默认使用 `cpu`。\n\n### 2.2 登入登陆节点\n- 进入登陆节点后，会有一些基本的信息提示\n\u003Cimg width=\"1512\" height=\"867\" alt=\"image\" src=\"/posts/usingSlurm/login-default.png\" />\n\n- 在个人目录下，有个共享文件夹，你可以在这放置共享文件，如协作目录等\n\u003Cimg width=\"1512\" height=\"867\" alt=\"image\" src=\"/posts/usingSlurm/shared.png\" />\n\n  共享目录默认的文件权限为 `所有人可创建; 文件只有创建者可读写; 他人只读` ，如果需要创建协作目录，建议参考以下命令\n  ```bash\n  # 如果协作目录是 你可读写，他人只读\n  chmod 777 \u003C你的协作目录>\n  # 如果协作目录下是 所有人可创建; 文件只有创建者可读写，他人只读\n  chmod 1777 \u003C你的协作目录>\n  ```\n\n\n### 2.3 查看集群信息\n- 你可以使用 `sinfo` 查看节点和分区信息\n\u003Cimg width=\"1512\" height=\"867\" alt=\"image\" src=\"/posts/usingSlurm/sinfo.png\" />\n\n- 你可以使用 `module ava` 支持的查看软件包模块\n\u003Cimg width=\"1512\" height=\"867\" alt=\"image\" src=\"/posts/usingSlurm/module-ava.png\" />\n  之后，你可以使用module load加载你想要的软件包\n\n### 2.4 提交作业示例\n- **GPU 作业**：**系统会自动分配一张显卡**。如需多卡，请使用 `-G` 或 `--gres` 参数显式指定。\n  ```bash\n  # 自动分配一张显卡（默认）\n  sbatch -p gpu -c 4 your_program\n\n  # 显式指定使用4张显卡\n  sbatch -p gpu -G 4 --cpus-per-task=4 your_program\n  ```\n- **CPU 作业**：需自行指定核心数量。\n  ```bash\n  sbatch -p cpu -c 8 your_program\n  ```\n\n### 2.5 注意事项\n  因为登陆服务器是挂载在MacOS上的虚拟机，强烈不推荐在登陆服务器上进行如下任务：\n- 编译可执行程序\n- 运行计算任务\n\n如果需要编译可执行程序，请先编译好再上传到slurm上。\n\n如果需要测试程序，请直接使用`srun`进入交互式命令行执行。\n  ```bash\n  srun -p cpu -c 8 your_program\n  ```\n\n### 2.6 更多参考\n以下页面提供了详尽的 Slurm 使用指南，如有需要强烈建议阅读：\n\n- 上海交通大学超算平台: [Slurm 作业调度系统¶](https://docs.hpc.sjtu.edu.cn/job/slurm.html)\n\n- Slurm Worker Manager: [Slurm Documentation](https://slurm.schedmd.com/documentation.html)\n\n- CLab Server Docs: [LMod 使用指南](https://clab-hkust-gz.github.io/server-docs/userguide/lmod.html)\n\n- LMod: [User Guide for Lmod](https://lmod.readthedocs.io/en/latest/010_user.html)\n\n\n---\n\n## 3. 任务后台查看\n\n我们有个非常漂亮的后台，以下是它的使用教程\n\n### 3.1 访问 Dashboard\n打开浏览器访问 [https://slurm-dashboard.ai4qc.icu/](https://slurm-dashboard.ai4qc.icu/)。  \n若浏览器会话中无有效的 Access Token，系统将自动重定向至 Cloudflare 零信任网关重新登录。认证成功后，将跳转至 Dashboard, 即可查看作业状态、资源使用情况等。  \n\n\n\n更详细的使用说明，请阅读[Slurm-web/Overview](https://docs.rackslab.io/slurm-web/overview/overview.html)\n\u003Cimg width=\"1512\" height=\"867\" alt=\"image\" src=\"/posts/usingSlurm/slurm-web.png\" />\n\n---\n\n## 4. 密码管理\n\n~~以防你忘记密码了，虽然说这东西没啥用~~\n\n### 4.1 登录 profile 页面\n访问 [https://profile.ai4qc.icu/](https://profile.ai4qc.icu/) 并使用 GitHub OAuth 登录。\n\n### 4.2 修改密码\n在 **“修改帐户密码”** 区域，您可以通过以下两种方式验证身份：\n- **原密码**：输入当前密码。\n- **OAuth**：使用 GitHub 快速验证（推荐，邮箱验证暂不可用）。\n\n验证通过后，在右侧输入新密码两次，确保一致，点击 **提交** 即可。\n\n### 4.3 注意事项\n- 密码修改成功后，您会被强制登出，后续访问需使用新密码重新登录。\n- 请妥善保管密码，避免泄露。\n\n---\n\n如有任何问题，请联系系统管理员。","src/content/posts/usingSlurm/usingSlurm.md","48a9651ed6bf13f4",{"html":49,"metadata":50},"\u003Csection>\u003Ch1 id=\"slurm集群使用指南\">Slurm集群使用指南\u003Ca class=\"anchor\" href=\"#slurm集群使用指南\">\u003Cspan class=\"anchor-icon\" data-pagefind-ignore=\"\">#\u003C/span>\u003C/a>\u003C/h1>\u003Cp>欢迎使用本集群。本文档将引导您完成从环境配置到作业提交的完整流程，帮助您高效利用计算资源。\u003C/p>\u003Chr>\u003Csection>\u003Ch2 id=\"0-系统架构\">0. 系统架构\u003Ca class=\"anchor\" href=\"#0-系统架构\">\u003Cspan class=\"anchor-icon\" data-pagefind-ignore=\"\">#\u003C/span>\u003C/a>\u003C/h2>\u003Cp>集群由六台服务器组成，通过一台 \u003Cstrong>40G 以太网交换机\u003C/strong>互连，构建高速计算网络。\u003C/p>\u003C!-- ```mermaid\ngraph TD\n    Switch[Mellanox SX6012 40G 交换机]\n\n    Login[登录服务器]\n    GPU[\"GPU服务器\u003Cbr/>64c128t | 120GB RAM\u003Cbr/>8×NVIDIA 4090 48GB\"]\n    CPU1[\"CPU服务器1\u003Cbr/>48c96t | 128GB RAM\"]\n    CPU2[\"CPU服务器2\u003Cbr/>48c96t | 256GB RAM\"]\n    Storage[\"存储服务器\u003Cbr/>48TB 阵列\u003Cbr/>1TB NVMe SSD 缓存\u003Cbr/>256GB Optane PMEM\"]\n\n    Login --- Switch\n    GPU --- Switch\n    CPU1 --- Switch\n    CPU2 --- Switch\n    Storage --- Switch\n``` \n-->\u003Cp>\u003Cstrong>硬件配置明细\u003C/strong>：\u003C/p>\u003Cul>\n\u003Cli>\u003Cstrong>控制服务器\u003C/strong>：控制节点，用于作业调度、提供REST API。\u003C/li>\n\u003Cli>\u003Cstrong>登录服务器\u003C/strong>：用户接入节点，用于作业提交和管理。\u003C/li>\n\u003Cli>\u003Cstrong>GPU服务器\u003C/strong>：64核心128线程，120GB内存，8张NVIDIA 4090 48GB显卡。\u003C/li>\n\u003Cli>\u003Cstrong>CPU服务器1\u003C/strong>：48核心96线程，128GB内存。\u003C/li>\n\u003Cli>\u003Cstrong>CPU服务器2\u003C/strong>：48核心96线程，256GB内存。\u003C/li>\n\u003Cli>\u003Cstrong>存储服务器\u003C/strong>：48TB硬盘阵列，配备1TB NVMe SSD高速缓存和256GB Intel Optane PMEM超高速缓存。\u003C/li>\n\u003C/ul>\u003Cimg width=\"1512\" height=\"867\" alt=\"零信任平台入口\" src=\"/posts/usingSlurm/topology.png\">\u003Cp>注意：控制节点和登陆节点是一台mac mini上跑的虚拟机。因此，对于登陆节点，请不要再上面编译程序或者运行代码，基本上编不出来，编出来了你在计算节点上也跑不了\u003Cdel>你要交叉编译那我也没啥好说的\u003C/del>。\u003C/p>\u003Chr>\u003C/section>\u003Csection>\u003Ch2 id=\"1-环境与基本配置\">1. 环境与基本配置\u003Ca class=\"anchor\" href=\"#1-环境与基本配置\">\u003Cspan class=\"anchor-icon\" data-pagefind-ignore=\"\">#\u003C/span>\u003C/a>\u003C/h2>\u003Cp>出于安全因素，除SSH，所有的敏感业务访问都必须通过 \u003Ccode>Cloudflare 零信任平台\u003C/code> 进行登录，Cloudflare会记录你的用户态，单次有效期最长为24小时。你的密码修改，证书获取，以及查看我们的web面板，都属于敏感业务。\u003C/p>\u003Csection>\u003Ch3 id=\"11-登录零信任平台\">1.1 登录零信任平台\u003Ca class=\"anchor\" href=\"#11-登录零信任平台\">\u003Cspan class=\"anchor-icon\" data-pagefind-ignore=\"\">#\u003C/span>\u003C/a>\u003C/h3>\u003Cp>访问 \u003Ca href=\"https://ai4qc-hkust.cloudflareaccess.com/\">https://ai4qc-hkust.cloudflareaccess.com/\u003C/a>。\u003Cbr>\n\u003Cstrong>注意\u003C/strong>：必须使用已在 \u003Ccode>ai4qc\u003C/code> 组织内的 GitHub 帐户登录，否则无法获得授权。\u003Cbr>\n成功登录后，您将看到如下界面：\u003Cbr>\n\u003Cimg width=\"1512\" height=\"867\" alt=\"零信任平台入口\" src=\"/posts/usingSlurm/zt-entrypoint.png\">\u003C/p>\u003C/section>\u003Csection>\u003Ch3 id=\"12-访问用户管理界面\">1.2 访问用户管理界面\u003Ca class=\"anchor\" href=\"#12-访问用户管理界面\">\u003Cspan class=\"anchor-icon\" data-pagefind-ignore=\"\">#\u003C/span>\u003C/a>\u003C/h3>\u003Cp>点击零信任平台中的 \u003Cstrong>profile\u003C/strong> 或直接访问 \u003Ca href=\"https://profile.ai4qc.icu/\">https://profile.ai4qc.icu/\u003C/a> 进入用户管理界面。\u003Cbr>\n\u003Cimg width=\"1512\" height=\"867\" alt=\"image\" src=\"/posts/usingSlurm/go-ldap-login.png\">\u003C/p>\u003C/section>\u003Csection>\u003Ch3 id=\"13-首次登录与初始密码\">1.3 首次登录与初始密码\u003Ca class=\"anchor\" href=\"#13-首次登录与初始密码\">\u003Cspan class=\"anchor-icon\" data-pagefind-ignore=\"\">#\u003C/span>\u003C/a>\u003C/h3>\u003Cul>\n\u003Cli>点击 \u003Cstrong>OAuth 登录\u003C/strong>，使用您的 GitHub 账号授权。初次登录将自动完成用户注册。\u003C/li>\n\u003Cli>登录成功后进入个人主页。\u003Cstrong>新用户会弹出初始密码\u003C/strong>，请妥善保存；您可以立即修改或暂时忽略。\n\u003Cimg width=\"1512\" height=\"867\" alt=\"image\" src=\"/posts/usingSlurm/profile-page.png\">\n\u003C/li>\n\u003C/ul>\u003C/section>\u003Csection>\u003Ch3 id=\"14-获取-ssh-证书\">1.4 获取 SSH 证书\u003Ca class=\"anchor\" href=\"#14-获取-ssh-证书\">\u003Cspan class=\"anchor-icon\" data-pagefind-ignore=\"\">#\u003C/span>\u003C/a>\u003C/h3>\u003Cp>在个人主页中，找到 \u003Cstrong>“生成并下载 SSH 证书”\u003C/strong> 区域，点击 \u003Cstrong>“生成”\u003C/strong> 按钮。系统将生成一对证书并自动下载为一个压缩包：\u003C/p>\u003Cul>\n\u003Cli>\u003Cstrong>私钥文件\u003C/strong>：文件名格式为 \u003Ccode>[用户名]-[日期]\u003C/code>（例如 \u003Ccode>zhangsan-20250302\u003C/code>）\u003C/li>\n\u003Cli>\u003Cstrong>签名证书\u003C/strong>：文件名格式为 \u003Ccode>[用户名]-[日期]-cert.crt\u003C/code>（例如 \u003Ccode>zhangsan-20250302-cert.crt\u003C/code>）\u003C/li>\n\u003C/ul>\u003Cp>解压后，您可以选择以下任一方式使用证书连接集群：\u003C/p>\u003Csection>\u003Ch4 id=\"140-注意事项\">1.4.0 注意事项\u003Ca class=\"anchor\" href=\"#140-注意事项\">\u003Cspan class=\"anchor-icon\" data-pagefind-ignore=\"\">#\u003C/span>\u003C/a>\u003C/h4>\u003Cdiv class=\"expressive-code\">\u003Clink rel=\"stylesheet\" href=\"/_astro/ec.4fsv9.css\">\u003Cscript type=\"module\" src=\"/_astro/ec.g1fg5.js\">\u003C/script>\u003Cfigure class=\"frame is-terminal\">\u003Cfigcaption class=\"header\">\u003Cspan class=\"title\">\u003C/span>\u003Cspan class=\"sr-only\">Terminal window\u003C/span>\u003C/figcaption>\u003Cpre data-language=\"bash\" class=\"wrap\" style=\"--ecMaxLine:22ch\">\u003Ccode>\u003Cdiv class=\"ec-line\">\u003Cdiv class=\"gutter\">\u003Cdiv class=\"ln\" aria-hidden=\"true\">1\u003C/div>\u003C/div>\u003Cdiv class=\"code\">\u003Cspan style=\"--0:#B392F0;--1:#B392F0\">以防有人不仔细看，SSH\u003C/span>\u003Cspan style=\"--0:#E1E4E8;--1:#E1E4E8\"> \u003C/span>\u003Cspan style=\"--0:#9ECBFF;--1:#9ECBFF\">记得加端口9922\u003C/span>\u003C/div>\u003C/div>\u003C/code>\u003Cbutton class=\"copy-btn\" aria-label=\"Copy code\">\u003Cdiv class=\"copy-btn-icon\">\u003Csvg viewBox=\"0 -960 960 960\" xmlns=\"http://www.w3.org/2000/svg\" class=\"copy-btn-icon copy-icon\">\u003Cpath d=\"M368.37-237.37q-34.48 0-58.74-24.26-24.26-24.26-24.26-58.74v-474.26q0-34.48 24.26-58.74 24.26-24.26 58.74-24.26h378.26q34.48 0 58.74 24.26 24.26 24.26 24.26 58.74v474.26q0 34.48-24.26 58.74-24.26 24.26-58.74 24.26H368.37Zm0-83h378.26v-474.26H368.37v474.26Zm-155 238q-34.48 0-58.74-24.26-24.26-24.26-24.26-58.74v-515.76q0-17.45 11.96-29.48 11.97-12.02 29.33-12.02t29.54 12.02q12.17 12.03 12.17 29.48v515.76h419.76q17.45 0 29.48 11.96 12.02 11.97 12.02 29.33t-12.02 29.54q-12.03 12.17-29.48 12.17H213.37Zm155-238v-474.26 474.26Z\">\u003C/path>\u003C/svg>\u003Csvg viewBox=\"0 -960 960 960\" xmlns=\"http://www.w3.org/2000/svg\" class=\"copy-btn-icon success-icon\">\u003Cpath d=\"m389-377.13 294.7-294.7q12.58-12.67 29.52-12.67 16.93 0 29.61 12.67 12.67 12.68 12.67 29.53 0 16.86-12.28 29.14L419.07-288.41q-12.59 12.67-29.52 12.67-16.94 0-29.62-12.67L217.41-430.93q-12.67-12.68-12.79-29.45-.12-16.77 12.55-29.45 12.68-12.67 29.62-12.67 16.93 0 29.28 12.67L389-377.13Z\">\u003C/path>\u003C/svg>\u003C/div>\u003C/button>\u003C/pre>\u003C/figure>\u003C/div>\u003C/section>\u003Csection>\u003Ch4 id=\"141-使用命令行直接登录\">1.4.1 使用命令行直接登录\u003Ca class=\"anchor\" href=\"#141-使用命令行直接登录\">\u003Cspan class=\"anchor-icon\" data-pagefind-ignore=\"\">#\u003C/span>\u003C/a>\u003C/h4>\u003Cdiv class=\"expressive-code\">\u003Cfigure class=\"frame is-terminal\">\u003Cfigcaption class=\"header\">\u003Cspan class=\"title\">\u003C/span>\u003Cspan class=\"sr-only\">Terminal window\u003C/span>\u003C/figcaption>\u003Cpre data-language=\"bash\" class=\"wrap\" style=\"--ecMaxLine:67ch\">\u003Ccode>\u003Cdiv class=\"ec-line\">\u003Cdiv class=\"gutter\">\u003Cdiv class=\"ln\" aria-hidden=\"true\">1\u003C/div>\u003C/div>\u003Cdiv class=\"code\">\u003Cspan style=\"--0:#B392F0;--1:#B392F0\">ssh\u003C/span>\u003Cspan style=\"--0:#E1E4E8;--1:#E1E4E8\"> \u003C/span>\u003Cspan style=\"--0:#79B8FF;--1:#79B8FF\">-i\u003C/span>\u003Cspan style=\"--0:#E1E4E8;--1:#E1E4E8\"> \u003C/span>\u003Cspan style=\"--0:#9ECBFF;--1:#9ECBFF\">/path/to/private_key_file\u003C/span>\u003Cspan style=\"--0:#E1E4E8;--1:#E1E4E8\"> \u003C/span>\u003Cspan style=\"--0:#9ECBFF;--1:#9ECBFF\">&#x3C;username>@login.ai4qc.icu\u003C/span>\u003Cspan style=\"--0:#E1E4E8;--1:#E1E4E8\"> \u003C/span>\u003Cspan style=\"--0:#79B8FF;--1:#79B8FF\">-p\u003C/span>\u003Cspan style=\"--0:#E1E4E8;--1:#E1E4E8\"> \u003C/span>\u003Cspan style=\"--0:#79B8FF;--1:#79B8FF\">9922\u003C/span>\u003C/div>\u003C/div>\u003C/code>\u003Cbutton class=\"copy-btn\" aria-label=\"Copy code\">\u003Cdiv class=\"copy-btn-icon\">\u003Csvg viewBox=\"0 -960 960 960\" xmlns=\"http://www.w3.org/2000/svg\" class=\"copy-btn-icon copy-icon\">\u003Cpath d=\"M368.37-237.37q-34.48 0-58.74-24.26-24.26-24.26-24.26-58.74v-474.26q0-34.48 24.26-58.74 24.26-24.26 58.74-24.26h378.26q34.48 0 58.74 24.26 24.26 24.26 24.26 58.74v474.26q0 34.48-24.26 58.74-24.26 24.26-58.74 24.26H368.37Zm0-83h378.26v-474.26H368.37v474.26Zm-155 238q-34.48 0-58.74-24.26-24.26-24.26-24.26-58.74v-515.76q0-17.45 11.96-29.48 11.97-12.02 29.33-12.02t29.54 12.02q12.17 12.03 12.17 29.48v515.76h419.76q17.45 0 29.48 11.96 12.02 11.97 12.02 29.33t-12.02 29.54q-12.03 12.17-29.48 12.17H213.37Zm155-238v-474.26 474.26Z\">\u003C/path>\u003C/svg>\u003Csvg viewBox=\"0 -960 960 960\" xmlns=\"http://www.w3.org/2000/svg\" class=\"copy-btn-icon success-icon\">\u003Cpath d=\"m389-377.13 294.7-294.7q12.58-12.67 29.52-12.67 16.93 0 29.61 12.67 12.67 12.68 12.67 29.53 0 16.86-12.28 29.14L419.07-288.41q-12.59 12.67-29.52 12.67-16.94 0-29.62-12.67L217.41-430.93q-12.67-12.68-12.79-29.45-.12-16.77 12.55-29.45 12.68-12.67 29.62-12.67 16.93 0 29.28 12.67L389-377.13Z\">\u003C/path>\u003C/svg>\u003C/div>\u003C/button>\u003C/pre>\u003C/figure>\u003C/div>\u003Cp>（SSH 客户端会自动寻找同名的证书文件，无需额外指定。）\u003C/p>\u003C/section>\u003Csection>\u003Ch4 id=\"142-配置-ssh-config\">1.4.2 配置 SSH config\u003Ca class=\"anchor\" href=\"#142-配置-ssh-config\">\u003Cspan class=\"anchor-icon\" data-pagefind-ignore=\"\">#\u003C/span>\u003C/a>\u003C/h4>\u003Cp>在 \u003Ccode>~/.ssh/config\u003C/code> 中添加如下配置：\u003C/p>\u003Cdiv class=\"expressive-code\">\u003Cfigure class=\"frame is-terminal\">\u003Cfigcaption class=\"header\">\u003Cspan class=\"title\">\u003C/span>\u003Cspan class=\"sr-only\">Terminal window\u003C/span>\u003C/figcaption>\u003Cpre data-language=\"bash\" class=\"wrap\" style=\"--ecMaxLine:42ch\">\u003Ccode>\u003Cdiv class=\"ec-line\">\u003Cdiv class=\"gutter\">\u003Cdiv class=\"ln\" aria-hidden=\"true\">1\u003C/div>\u003C/div>\u003Cdiv class=\"code\">\u003Cspan style=\"--0:#B392F0;--1:#B392F0\">Host\u003C/span>\u003Cspan style=\"--0:#E1E4E8;--1:#E1E4E8\"> \u003C/span>\u003Cspan style=\"--0:#9ECBFF;--1:#9ECBFF\">ai4qc\u003C/span>\u003C/div>\u003C/div>\u003Cdiv class=\"ec-line\" style=\"--ecIndent:4ch\">\u003Cdiv class=\"gutter\">\u003Cdiv class=\"ln\" aria-hidden=\"true\">2\u003C/div>\u003C/div>\u003Cdiv class=\"code\">\u003Cspan class=\"indent\">    \u003C/span>\u003Cspan style=\"--0:#B392F0;--1:#B392F0\">HostName\u003C/span>\u003Cspan style=\"--0:#E1E4E8;--1:#E1E4E8\"> \u003C/span>\u003Cspan style=\"--0:#9ECBFF;--1:#9ECBFF\">login.ai4qc.icu\u003C/span>\u003C/div>\u003C/div>\u003Cdiv class=\"ec-line\" style=\"--ecIndent:4ch\">\u003Cdiv class=\"gutter\">\u003Cdiv class=\"ln\" aria-hidden=\"true\">3\u003C/div>\u003C/div>\u003Cdiv class=\"code\">\u003Cspan class=\"indent\">    \u003C/span>\u003Cspan style=\"--0:#B392F0;--1:#B392F0\">User\u003C/span>\u003Cspan style=\"--0:#E1E4E8;--1:#E1E4E8\"> \u003C/span>\u003Cspan style=\"--0:#9ECBFF;--1:#9ECBFF\">&#x3C;your-username>\u003C/span>\u003C/div>\u003C/div>\u003Cdiv class=\"ec-line\" style=\"--ecIndent:4ch\">\u003Cdiv class=\"gutter\">\u003Cdiv class=\"ln\" aria-hidden=\"true\">4\u003C/div>\u003C/div>\u003Cdiv class=\"code\">\u003Cspan class=\"indent\">    \u003C/span>\u003Cspan style=\"--0:#B392F0;--1:#B392F0\">Port\u003C/span>\u003Cspan style=\"--0:#E1E4E8;--1:#E1E4E8\"> \u003C/span>\u003Cspan style=\"--0:#79B8FF;--1:#79B8FF\">9922\u003C/span>\u003C/div>\u003C/div>\u003Cdiv class=\"ec-line\" style=\"--ecIndent:4ch\">\u003Cdiv class=\"gutter\">\u003Cdiv class=\"ln\" aria-hidden=\"true\">5\u003C/div>\u003C/div>\u003Cdiv class=\"code\">\u003Cspan class=\"indent\">    \u003C/span>\u003Cspan style=\"--0:#B392F0;--1:#B392F0\">IdentityFile\u003C/span>\u003Cspan style=\"--0:#E1E4E8;--1:#E1E4E8\"> \u003C/span>\u003Cspan style=\"--0:#9ECBFF;--1:#9ECBFF\">/path/to/private_key_file\u003C/span>\u003C/div>\u003C/div>\u003Cdiv class=\"ec-line\" style=\"--ecIndent:4ch\">\u003Cdiv class=\"gutter\">\u003Cdiv class=\"ln\" aria-hidden=\"true\">6\u003C/div>\u003C/div>\u003Cdiv class=\"code\">\u003Cspan class=\"indent\">    \u003C/span>\u003Cspan style=\"--0:#B392F0;--1:#B392F0\">CertificateFile\u003C/span>\u003Cspan style=\"--0:#E1E4E8;--1:#E1E4E8\"> \u003C/span>\u003Cspan style=\"--0:#9ECBFF;--1:#9ECBFF\">/path/to/cert_file\u003C/span>\u003C/div>\u003C/div>\u003C/code>\u003Cbutton class=\"copy-btn\" aria-label=\"Copy code\">\u003Cdiv class=\"copy-btn-icon\">\u003Csvg viewBox=\"0 -960 960 960\" xmlns=\"http://www.w3.org/2000/svg\" class=\"copy-btn-icon copy-icon\">\u003Cpath d=\"M368.37-237.37q-34.48 0-58.74-24.26-24.26-24.26-24.26-58.74v-474.26q0-34.48 24.26-58.74 24.26-24.26 58.74-24.26h378.26q34.48 0 58.74 24.26 24.26 24.26 24.26 58.74v474.26q0 34.48-24.26 58.74-24.26 24.26-58.74 24.26H368.37Zm0-83h378.26v-474.26H368.37v474.26Zm-155 238q-34.48 0-58.74-24.26-24.26-24.26-24.26-58.74v-515.76q0-17.45 11.96-29.48 11.97-12.02 29.33-12.02t29.54 12.02q12.17 12.03 12.17 29.48v515.76h419.76q17.45 0 29.48 11.96 12.02 11.97 12.02 29.33t-12.02 29.54q-12.03 12.17-29.48 12.17H213.37Zm155-238v-474.26 474.26Z\">\u003C/path>\u003C/svg>\u003Csvg viewBox=\"0 -960 960 960\" xmlns=\"http://www.w3.org/2000/svg\" class=\"copy-btn-icon success-icon\">\u003Cpath d=\"m389-377.13 294.7-294.7q12.58-12.67 29.52-12.67 16.93 0 29.61 12.67 12.67 12.68 12.67 29.53 0 16.86-12.28 29.14L419.07-288.41q-12.59 12.67-29.52 12.67-16.94 0-29.62-12.67L217.41-430.93q-12.67-12.68-12.79-29.45-.12-16.77 12.55-29.45 12.68-12.67 29.62-12.67 16.93 0 29.28 12.67L389-377.13Z\">\u003C/path>\u003C/svg>\u003C/div>\u003C/button>\u003C/pre>\u003C/figure>\u003C/div>\u003Cp>之后可直接使用 \u003Ccode>ssh ai4qc\u003C/code> 登录。\u003C/p>\u003C/section>\u003Csection>\u003Ch4 id=\"143-在-vs-code-中使用\">1.4.3 在 VS Code 中使用\u003Ca class=\"anchor\" href=\"#143-在-vs-code-中使用\">\u003Cspan class=\"anchor-icon\" data-pagefind-ignore=\"\">#\u003C/span>\u003C/a>\u003C/h4>\u003Cp>参考官方文档 \u003Ca href=\"https://code.visualstudio.com/docs/remote/troubleshooting#_improving-your-security-with-a-dedicated-key\">Improving your security with a dedicated key\u003C/a>，配置 Remote-SSH 使用证书。\u003C/p>\u003C/section>\u003Csection>\u003Ch4 id=\"144-在-termius-中使用\">1.4.4 在 Termius 中使用\u003Ca class=\"anchor\" href=\"#144-在-termius-中使用\">\u003Cspan class=\"anchor-icon\" data-pagefind-ignore=\"\">#\u003C/span>\u003C/a>\u003C/h4>\u003Cp>Termius 支持直接导入 SSH 证书，请参阅 \u003Ca href=\"https://termius.com/documentation/ssh-certificates\">Import SSH Certificate\u003C/a> 完成设置。\u003C/p>\u003C/section>\u003C/section>\u003Csection>\u003Ch3 id=\"15-配置终端可选\">1.5 配置终端（可选）\u003Ca class=\"anchor\" href=\"#15-配置终端可选\">\u003Cspan class=\"anchor-icon\" data-pagefind-ignore=\"\">#\u003C/span>\u003C/a>\u003C/h3>\u003Cp>默认登录 Shell 为 \u003Cstrong>zsh\u003C/strong>，其具备强大的自动补全和主题功能。如需切换为 bash，请在登录后进入 \u003Cstrong>“终端设置”\u003C/strong> → \u003Cstrong>“Shell”\u003C/strong> 进行修改。\u003C/p>\u003C/section>\u003Csection>\u003Ch3 id=\"16-连接集群\">1.6 连接集群\u003Ca class=\"anchor\" href=\"#16-连接集群\">\u003Cspan class=\"anchor-icon\" data-pagefind-ignore=\"\">#\u003C/span>\u003C/a>\u003C/h3>\u003Cp>完成上述配置后，即可通过 SSH 正常登录集群：\u003C/p>\u003Cdiv class=\"expressive-code\">\u003Cfigure class=\"frame is-terminal\">\u003Cfigcaption class=\"header\">\u003Cspan class=\"title\">\u003C/span>\u003Cspan class=\"sr-only\">Terminal window\u003C/span>\u003C/figcaption>\u003Cpre data-language=\"bash\" class=\"wrap\" style=\"--ecMaxLine:38ch\">\u003Ccode>\u003Cdiv class=\"ec-line\">\u003Cdiv class=\"gutter\">\u003Cdiv class=\"ln\" aria-hidden=\"true\">1\u003C/div>\u003C/div>\u003Cdiv class=\"code\">\u003Cspan style=\"--0:#B392F0;--1:#B392F0\">ssh\u003C/span>\u003Cspan style=\"--0:#E1E4E8;--1:#E1E4E8\"> \u003C/span>\u003Cspan style=\"--0:#9ECBFF;--1:#9ECBFF\">&#x3C;username>@login.ai4qc.icu\u003C/span>\u003Cspan style=\"--0:#E1E4E8;--1:#E1E4E8\"> \u003C/span>\u003Cspan style=\"--0:#79B8FF;--1:#79B8FF\">-p\u003C/span>\u003Cspan style=\"--0:#E1E4E8;--1:#E1E4E8\"> \u003C/span>\u003Cspan style=\"--0:#79B8FF;--1:#79B8FF\">9922\u003C/span>\u003C/div>\u003C/div>\u003C/code>\u003Cbutton class=\"copy-btn\" aria-label=\"Copy code\">\u003Cdiv class=\"copy-btn-icon\">\u003Csvg viewBox=\"0 -960 960 960\" xmlns=\"http://www.w3.org/2000/svg\" class=\"copy-btn-icon copy-icon\">\u003Cpath d=\"M368.37-237.37q-34.48 0-58.74-24.26-24.26-24.26-24.26-58.74v-474.26q0-34.48 24.26-58.74 24.26-24.26 58.74-24.26h378.26q34.48 0 58.74 24.26 24.26 24.26 24.26 58.74v474.26q0 34.48-24.26 58.74-24.26 24.26-58.74 24.26H368.37Zm0-83h378.26v-474.26H368.37v474.26Zm-155 238q-34.48 0-58.74-24.26-24.26-24.26-24.26-58.74v-515.76q0-17.45 11.96-29.48 11.97-12.02 29.33-12.02t29.54 12.02q12.17 12.03 12.17 29.48v515.76h419.76q17.45 0 29.48 11.96 12.02 11.97 12.02 29.33t-12.02 29.54q-12.03 12.17-29.48 12.17H213.37Zm155-238v-474.26 474.26Z\">\u003C/path>\u003C/svg>\u003Csvg viewBox=\"0 -960 960 960\" xmlns=\"http://www.w3.org/2000/svg\" class=\"copy-btn-icon success-icon\">\u003Cpath d=\"m389-377.13 294.7-294.7q12.58-12.67 29.52-12.67 16.93 0 29.61 12.67 12.67 12.68 12.67 29.53 0 16.86-12.28 29.14L419.07-288.41q-12.59 12.67-29.52 12.67-16.94 0-29.62-12.67L217.41-430.93q-12.67-12.68-12.79-29.45-.12-16.77 12.55-29.45 12.68-12.67 29.62-12.67 16.93 0 29.28 12.67L389-377.13Z\">\u003C/path>\u003C/svg>\u003C/div>\u003C/button>\u003C/pre>\u003C/figure>\u003C/div>\u003Chr>\u003C/section>\u003C/section>\u003Csection>\u003Ch2 id=\"2-slurm-作业调度系统使用\">2. Slurm 作业调度系统使用\u003Ca class=\"anchor\" href=\"#2-slurm-作业调度系统使用\">\u003Cspan class=\"anchor-icon\" data-pagefind-ignore=\"\">#\u003C/span>\u003C/a>\u003C/h2>\u003Cp>一些基本说明\u003C/p>\u003Csection>\u003Ch3 id=\"21-分区说明\">2.1 分区说明\u003Ca class=\"anchor\" href=\"#21-分区说明\">\u003Cspan class=\"anchor-icon\" data-pagefind-ignore=\"\">#\u003C/span>\u003C/a>\u003C/h3>\u003Cp>集群包含两个分区（Partition）：\u003C/p>\u003Cul>\n\u003Cli>\u003Cstrong>cpu\u003C/strong>：用于纯 CPU 计算任务（默认分区）。\u003C/li>\n\u003Cli>\u003Cstrong>gpu\u003C/strong>：用于 GPU 加速任务。\u003C/li>\n\u003C/ul>\u003Cp>提交作业时若未指定分区，默认使用 \u003Ccode>cpu\u003C/code>。\u003C/p>\u003C/section>\u003Csection>\u003Ch3 id=\"22-登入登陆节点\">2.2 登入登陆节点\u003Ca class=\"anchor\" href=\"#22-登入登陆节点\">\u003Cspan class=\"anchor-icon\" data-pagefind-ignore=\"\">#\u003C/span>\u003C/a>\u003C/h3>\u003Cul>\n\u003Cli>\n\u003Cp>进入登陆节点后，会有一些基本的信息提示\u003C/p>\n\u003Cimg width=\"1512\" height=\"867\" alt=\"image\" src=\"/posts/usingSlurm/login-default.png\">\n\u003C/li>\n\u003Cli>\n\u003Cp>在个人目录下，有个共享文件夹，你可以在这放置共享文件，如协作目录等\u003C/p>\n\u003Cimg width=\"1512\" height=\"867\" alt=\"image\" src=\"/posts/usingSlurm/shared.png\">\n\u003Cp>共享目录默认的文件权限为 \u003Ccode>所有人可创建; 文件只有创建者可读写; 他人只读\u003C/code> ，如果需要创建协作目录，建议参考以下命令\u003C/p>\n\u003Cdiv class=\"expressive-code\">\u003Cfigure class=\"frame is-terminal\">\u003Cfigcaption class=\"header\">\u003Cspan class=\"title\">\u003C/span>\u003Cspan class=\"sr-only\">Terminal window\u003C/span>\u003C/figcaption>\u003Cpre data-language=\"bash\" class=\"wrap\" style=\"--ecMaxLine:34ch\">\u003Ccode>\u003Cdiv class=\"ec-line\">\u003Cdiv class=\"gutter\">\u003Cdiv class=\"ln\" aria-hidden=\"true\">1\u003C/div>\u003C/div>\u003Cdiv class=\"code\">\u003Cspan style=\"--0:#99A0A6;--1:#99A0A6\"># 如果协作目录是 你可读写，他人只读\u003C/span>\u003C/div>\u003C/div>\u003Cdiv class=\"ec-line\">\u003Cdiv class=\"gutter\">\u003Cdiv class=\"ln\" aria-hidden=\"true\">2\u003C/div>\u003C/div>\u003Cdiv class=\"code\">\u003Cspan style=\"--0:#B392F0;--1:#B392F0\">chmod\u003C/span>\u003Cspan style=\"--0:#E1E4E8;--1:#E1E4E8\"> \u003C/span>\u003Cspan style=\"--0:#79B8FF;--1:#79B8FF\">777\u003C/span>\u003Cspan style=\"--0:#E1E4E8;--1:#E1E4E8\"> \u003C/span>\u003Cspan style=\"--0:#9ECBFF;--1:#9ECBFF\">&#x3C;你的协作目录>\u003C/span>\u003C/div>\u003C/div>\u003Cdiv class=\"ec-line\">\u003Cdiv class=\"gutter\">\u003Cdiv class=\"ln\" aria-hidden=\"true\">3\u003C/div>\u003C/div>\u003Cdiv class=\"code\">\u003Cspan style=\"--0:#99A0A6;--1:#99A0A6\"># 如果协作目录下是 所有人可创建; 文件只有创建者可读写，他人只读\u003C/span>\u003C/div>\u003C/div>\u003Cdiv class=\"ec-line\">\u003Cdiv class=\"gutter\">\u003Cdiv class=\"ln\" aria-hidden=\"true\">4\u003C/div>\u003C/div>\u003Cdiv class=\"code\">\u003Cspan style=\"--0:#B392F0;--1:#B392F0\">chmod\u003C/span>\u003Cspan style=\"--0:#E1E4E8;--1:#E1E4E8\"> \u003C/span>\u003Cspan style=\"--0:#79B8FF;--1:#79B8FF\">1777\u003C/span>\u003Cspan style=\"--0:#E1E4E8;--1:#E1E4E8\"> \u003C/span>\u003Cspan style=\"--0:#9ECBFF;--1:#9ECBFF\">&#x3C;你的协作目录>\u003C/span>\u003C/div>\u003C/div>\u003C/code>\u003Cbutton class=\"copy-btn\" aria-label=\"Copy code\">\u003Cdiv class=\"copy-btn-icon\">\u003Csvg viewBox=\"0 -960 960 960\" xmlns=\"http://www.w3.org/2000/svg\" class=\"copy-btn-icon copy-icon\">\u003Cpath d=\"M368.37-237.37q-34.48 0-58.74-24.26-24.26-24.26-24.26-58.74v-474.26q0-34.48 24.26-58.74 24.26-24.26 58.74-24.26h378.26q34.48 0 58.74 24.26 24.26 24.26 24.26 58.74v474.26q0 34.48-24.26 58.74-24.26 24.26-58.74 24.26H368.37Zm0-83h378.26v-474.26H368.37v474.26Zm-155 238q-34.48 0-58.74-24.26-24.26-24.26-24.26-58.74v-515.76q0-17.45 11.96-29.48 11.97-12.02 29.33-12.02t29.54 12.02q12.17 12.03 12.17 29.48v515.76h419.76q17.45 0 29.48 11.96 12.02 11.97 12.02 29.33t-12.02 29.54q-12.03 12.17-29.48 12.17H213.37Zm155-238v-474.26 474.26Z\">\u003C/path>\u003C/svg>\u003Csvg viewBox=\"0 -960 960 960\" xmlns=\"http://www.w3.org/2000/svg\" class=\"copy-btn-icon success-icon\">\u003Cpath d=\"m389-377.13 294.7-294.7q12.58-12.67 29.52-12.67 16.93 0 29.61 12.67 12.67 12.68 12.67 29.53 0 16.86-12.28 29.14L419.07-288.41q-12.59 12.67-29.52 12.67-16.94 0-29.62-12.67L217.41-430.93q-12.67-12.68-12.79-29.45-.12-16.77 12.55-29.45 12.68-12.67 29.62-12.67 16.93 0 29.28 12.67L389-377.13Z\">\u003C/path>\u003C/svg>\u003C/div>\u003C/button>\u003C/pre>\u003C/figure>\u003C/div>\n\u003C/li>\n\u003C/ul>\u003C/section>\u003Csection>\u003Ch3 id=\"23-查看集群信息\">2.3 查看集群信息\u003Ca class=\"anchor\" href=\"#23-查看集群信息\">\u003Cspan class=\"anchor-icon\" data-pagefind-ignore=\"\">#\u003C/span>\u003C/a>\u003C/h3>\u003Cul>\n\u003Cli>\n\u003Cp>你可以使用 \u003Ccode>sinfo\u003C/code> 查看节点和分区信息\u003C/p>\n\u003Cimg width=\"1512\" height=\"867\" alt=\"image\" src=\"/posts/usingSlurm/sinfo.png\">\n\u003C/li>\n\u003Cli>\n\u003Cp>你可以使用 \u003Ccode>module ava\u003C/code> 支持的查看软件包模块\u003C/p>\n\u003Cimg width=\"1512\" height=\"867\" alt=\"image\" src=\"/posts/usingSlurm/module-ava.png\">\n之后，你可以使用module load加载你想要的软件包\n\u003C/li>\n\u003C/ul>\u003C/section>\u003Csection>\u003Ch3 id=\"24-提交作业示例\">2.4 提交作业示例\u003Ca class=\"anchor\" href=\"#24-提交作业示例\">\u003Cspan class=\"anchor-icon\" data-pagefind-ignore=\"\">#\u003C/span>\u003C/a>\u003C/h3>\u003Cul>\n\u003Cli>\u003Cstrong>GPU 作业\u003C/strong>：\u003Cstrong>系统会自动分配一张显卡\u003C/strong>。如需多卡，请使用 \u003Ccode>-G\u003C/code> 或 \u003Ccode>--gres\u003C/code> 参数显式指定。\n\u003Cdiv class=\"expressive-code\">\u003Cfigure class=\"frame is-terminal\">\u003Cfigcaption class=\"header\">\u003Cspan class=\"title\">\u003C/span>\u003Cspan class=\"sr-only\">Terminal window\u003C/span>\u003C/figcaption>\u003Cpre data-language=\"bash\" class=\"wrap\" style=\"--ecMaxLine:49ch\">\u003Ccode>\u003Cdiv class=\"ec-line\">\u003Cdiv class=\"gutter\">\u003Cdiv class=\"ln\" aria-hidden=\"true\">1\u003C/div>\u003C/div>\u003Cdiv class=\"code\">\u003Cspan style=\"--0:#99A0A6;--1:#99A0A6\"># 自动分配一张显卡（默认）\u003C/span>\u003C/div>\u003C/div>\u003Cdiv class=\"ec-line\">\u003Cdiv class=\"gutter\">\u003Cdiv class=\"ln\" aria-hidden=\"true\">2\u003C/div>\u003C/div>\u003Cdiv class=\"code\">\u003Cspan style=\"--0:#B392F0;--1:#B392F0\">sbatch\u003C/span>\u003Cspan style=\"--0:#E1E4E8;--1:#E1E4E8\"> \u003C/span>\u003Cspan style=\"--0:#79B8FF;--1:#79B8FF\">-p\u003C/span>\u003Cspan style=\"--0:#E1E4E8;--1:#E1E4E8\"> \u003C/span>\u003Cspan style=\"--0:#9ECBFF;--1:#9ECBFF\">gpu\u003C/span>\u003Cspan style=\"--0:#E1E4E8;--1:#E1E4E8\"> \u003C/span>\u003Cspan style=\"--0:#79B8FF;--1:#79B8FF\">-c\u003C/span>\u003Cspan style=\"--0:#E1E4E8;--1:#E1E4E8\"> \u003C/span>\u003Cspan style=\"--0:#79B8FF;--1:#79B8FF\">4\u003C/span>\u003Cspan style=\"--0:#E1E4E8;--1:#E1E4E8\"> \u003C/span>\u003Cspan style=\"--0:#9ECBFF;--1:#9ECBFF\">your_program\u003C/span>\u003C/div>\u003C/div>\u003Cdiv class=\"ec-line\">\u003Cdiv class=\"gutter\">\u003Cdiv class=\"ln\" aria-hidden=\"true\">3\u003C/div>\u003C/div>\u003Cdiv class=\"code\">\n\u003C/div>\u003C/div>\u003Cdiv class=\"ec-line\">\u003Cdiv class=\"gutter\">\u003Cdiv class=\"ln\" aria-hidden=\"true\">4\u003C/div>\u003C/div>\u003Cdiv class=\"code\">\u003Cspan style=\"--0:#99A0A6;--1:#99A0A6\"># 显式指定使用4张显卡\u003C/span>\u003C/div>\u003C/div>\u003Cdiv class=\"ec-line\">\u003Cdiv class=\"gutter\">\u003Cdiv class=\"ln\" aria-hidden=\"true\">5\u003C/div>\u003C/div>\u003Cdiv class=\"code\">\u003Cspan style=\"--0:#B392F0;--1:#B392F0\">sbatch\u003C/span>\u003Cspan style=\"--0:#E1E4E8;--1:#E1E4E8\"> \u003C/span>\u003Cspan style=\"--0:#79B8FF;--1:#79B8FF\">-p\u003C/span>\u003Cspan style=\"--0:#E1E4E8;--1:#E1E4E8\"> \u003C/span>\u003Cspan style=\"--0:#9ECBFF;--1:#9ECBFF\">gpu\u003C/span>\u003Cspan style=\"--0:#E1E4E8;--1:#E1E4E8\"> \u003C/span>\u003Cspan style=\"--0:#79B8FF;--1:#79B8FF\">-G\u003C/span>\u003Cspan style=\"--0:#E1E4E8;--1:#E1E4E8\"> \u003C/span>\u003Cspan style=\"--0:#79B8FF;--1:#79B8FF\">4\u003C/span>\u003Cspan style=\"--0:#E1E4E8;--1:#E1E4E8\"> \u003C/span>\u003Cspan style=\"--0:#79B8FF;--1:#79B8FF\">--cpus-per-task=4\u003C/span>\u003Cspan style=\"--0:#E1E4E8;--1:#E1E4E8\"> \u003C/span>\u003Cspan style=\"--0:#9ECBFF;--1:#9ECBFF\">your_program\u003C/span>\u003C/div>\u003C/div>\u003C/code>\u003Cbutton class=\"copy-btn\" aria-label=\"Copy code\">\u003Cdiv class=\"copy-btn-icon\">\u003Csvg viewBox=\"0 -960 960 960\" xmlns=\"http://www.w3.org/2000/svg\" class=\"copy-btn-icon copy-icon\">\u003Cpath d=\"M368.37-237.37q-34.48 0-58.74-24.26-24.26-24.26-24.26-58.74v-474.26q0-34.48 24.26-58.74 24.26-24.26 58.74-24.26h378.26q34.48 0 58.74 24.26 24.26 24.26 24.26 58.74v474.26q0 34.48-24.26 58.74-24.26 24.26-58.74 24.26H368.37Zm0-83h378.26v-474.26H368.37v474.26Zm-155 238q-34.48 0-58.74-24.26-24.26-24.26-24.26-58.74v-515.76q0-17.45 11.96-29.48 11.97-12.02 29.33-12.02t29.54 12.02q12.17 12.03 12.17 29.48v515.76h419.76q17.45 0 29.48 11.96 12.02 11.97 12.02 29.33t-12.02 29.54q-12.03 12.17-29.48 12.17H213.37Zm155-238v-474.26 474.26Z\">\u003C/path>\u003C/svg>\u003Csvg viewBox=\"0 -960 960 960\" xmlns=\"http://www.w3.org/2000/svg\" class=\"copy-btn-icon success-icon\">\u003Cpath d=\"m389-377.13 294.7-294.7q12.58-12.67 29.52-12.67 16.93 0 29.61 12.67 12.67 12.68 12.67 29.53 0 16.86-12.28 29.14L419.07-288.41q-12.59 12.67-29.52 12.67-16.94 0-29.62-12.67L217.41-430.93q-12.67-12.68-12.79-29.45-.12-16.77 12.55-29.45 12.68-12.67 29.62-12.67 16.93 0 29.28 12.67L389-377.13Z\">\u003C/path>\u003C/svg>\u003C/div>\u003C/button>\u003C/pre>\u003C/figure>\u003C/div>\n\u003C/li>\n\u003Cli>\u003Cstrong>CPU 作业\u003C/strong>：需自行指定核心数量。\n\u003Cdiv class=\"expressive-code\">\u003Cfigure class=\"frame is-terminal\">\u003Cfigcaption class=\"header\">\u003Cspan class=\"title\">\u003C/span>\u003Cspan class=\"sr-only\">Terminal window\u003C/span>\u003C/figcaption>\u003Cpre data-language=\"bash\" class=\"wrap\" style=\"--ecMaxLine:31ch\">\u003Ccode>\u003Cdiv class=\"ec-line\">\u003Cdiv class=\"gutter\">\u003Cdiv class=\"ln\" aria-hidden=\"true\">1\u003C/div>\u003C/div>\u003Cdiv class=\"code\">\u003Cspan style=\"--0:#B392F0;--1:#B392F0\">sbatch\u003C/span>\u003Cspan style=\"--0:#E1E4E8;--1:#E1E4E8\"> \u003C/span>\u003Cspan style=\"--0:#79B8FF;--1:#79B8FF\">-p\u003C/span>\u003Cspan style=\"--0:#E1E4E8;--1:#E1E4E8\"> \u003C/span>\u003Cspan style=\"--0:#9ECBFF;--1:#9ECBFF\">cpu\u003C/span>\u003Cspan style=\"--0:#E1E4E8;--1:#E1E4E8\"> \u003C/span>\u003Cspan style=\"--0:#79B8FF;--1:#79B8FF\">-c\u003C/span>\u003Cspan style=\"--0:#E1E4E8;--1:#E1E4E8\"> \u003C/span>\u003Cspan style=\"--0:#79B8FF;--1:#79B8FF\">8\u003C/span>\u003Cspan style=\"--0:#E1E4E8;--1:#E1E4E8\"> \u003C/span>\u003Cspan style=\"--0:#9ECBFF;--1:#9ECBFF\">your_program\u003C/span>\u003C/div>\u003C/div>\u003C/code>\u003Cbutton class=\"copy-btn\" aria-label=\"Copy code\">\u003Cdiv class=\"copy-btn-icon\">\u003Csvg viewBox=\"0 -960 960 960\" xmlns=\"http://www.w3.org/2000/svg\" class=\"copy-btn-icon copy-icon\">\u003Cpath d=\"M368.37-237.37q-34.48 0-58.74-24.26-24.26-24.26-24.26-58.74v-474.26q0-34.48 24.26-58.74 24.26-24.26 58.74-24.26h378.26q34.48 0 58.74 24.26 24.26 24.26 24.26 58.74v474.26q0 34.48-24.26 58.74-24.26 24.26-58.74 24.26H368.37Zm0-83h378.26v-474.26H368.37v474.26Zm-155 238q-34.48 0-58.74-24.26-24.26-24.26-24.26-58.74v-515.76q0-17.45 11.96-29.48 11.97-12.02 29.33-12.02t29.54 12.02q12.17 12.03 12.17 29.48v515.76h419.76q17.45 0 29.48 11.96 12.02 11.97 12.02 29.33t-12.02 29.54q-12.03 12.17-29.48 12.17H213.37Zm155-238v-474.26 474.26Z\">\u003C/path>\u003C/svg>\u003Csvg viewBox=\"0 -960 960 960\" xmlns=\"http://www.w3.org/2000/svg\" class=\"copy-btn-icon success-icon\">\u003Cpath d=\"m389-377.13 294.7-294.7q12.58-12.67 29.52-12.67 16.93 0 29.61 12.67 12.67 12.68 12.67 29.53 0 16.86-12.28 29.14L419.07-288.41q-12.59 12.67-29.52 12.67-16.94 0-29.62-12.67L217.41-430.93q-12.67-12.68-12.79-29.45-.12-16.77 12.55-29.45 12.68-12.67 29.62-12.67 16.93 0 29.28 12.67L389-377.13Z\">\u003C/path>\u003C/svg>\u003C/div>\u003C/button>\u003C/pre>\u003C/figure>\u003C/div>\n\u003C/li>\n\u003C/ul>\u003C/section>\u003Csection>\u003Ch3 id=\"25-注意事项\">2.5 注意事项\u003Ca class=\"anchor\" href=\"#25-注意事项\">\u003Cspan class=\"anchor-icon\" data-pagefind-ignore=\"\">#\u003C/span>\u003C/a>\u003C/h3>\u003Cp>因为登陆服务器是挂载在MacOS上的虚拟机，强烈不推荐在登陆服务器上进行如下任务：\u003C/p>\u003Cul>\n\u003Cli>编译可执行程序\u003C/li>\n\u003Cli>运行计算任务\u003C/li>\n\u003C/ul>\u003Cp>如果需要编译可执行程序，请先编译好再上传到slurm上。\u003C/p>\u003Cp>如果需要测试程序，请直接使用\u003Ccode>srun\u003C/code>进入交互式命令行执行。\u003C/p>\u003Cdiv class=\"expressive-code\">\u003Cfigure class=\"frame is-terminal\">\u003Cfigcaption class=\"header\">\u003Cspan class=\"title\">\u003C/span>\u003Cspan class=\"sr-only\">Terminal window\u003C/span>\u003C/figcaption>\u003Cpre data-language=\"bash\" class=\"wrap\" style=\"--ecMaxLine:29ch\">\u003Ccode>\u003Cdiv class=\"ec-line\">\u003Cdiv class=\"gutter\">\u003Cdiv class=\"ln\" aria-hidden=\"true\">1\u003C/div>\u003C/div>\u003Cdiv class=\"code\">\u003Cspan style=\"--0:#B392F0;--1:#B392F0\">srun\u003C/span>\u003Cspan style=\"--0:#E1E4E8;--1:#E1E4E8\"> \u003C/span>\u003Cspan style=\"--0:#79B8FF;--1:#79B8FF\">-p\u003C/span>\u003Cspan style=\"--0:#E1E4E8;--1:#E1E4E8\"> \u003C/span>\u003Cspan style=\"--0:#9ECBFF;--1:#9ECBFF\">cpu\u003C/span>\u003Cspan style=\"--0:#E1E4E8;--1:#E1E4E8\"> \u003C/span>\u003Cspan style=\"--0:#79B8FF;--1:#79B8FF\">-c\u003C/span>\u003Cspan style=\"--0:#E1E4E8;--1:#E1E4E8\"> \u003C/span>\u003Cspan style=\"--0:#79B8FF;--1:#79B8FF\">8\u003C/span>\u003Cspan style=\"--0:#E1E4E8;--1:#E1E4E8\"> \u003C/span>\u003Cspan style=\"--0:#9ECBFF;--1:#9ECBFF\">your_program\u003C/span>\u003C/div>\u003C/div>\u003C/code>\u003Cbutton class=\"copy-btn\" aria-label=\"Copy code\">\u003Cdiv class=\"copy-btn-icon\">\u003Csvg viewBox=\"0 -960 960 960\" xmlns=\"http://www.w3.org/2000/svg\" class=\"copy-btn-icon copy-icon\">\u003Cpath d=\"M368.37-237.37q-34.48 0-58.74-24.26-24.26-24.26-24.26-58.74v-474.26q0-34.48 24.26-58.74 24.26-24.26 58.74-24.26h378.26q34.48 0 58.74 24.26 24.26 24.26 24.26 58.74v474.26q0 34.48-24.26 58.74-24.26 24.26-58.74 24.26H368.37Zm0-83h378.26v-474.26H368.37v474.26Zm-155 238q-34.48 0-58.74-24.26-24.26-24.26-24.26-58.74v-515.76q0-17.45 11.96-29.48 11.97-12.02 29.33-12.02t29.54 12.02q12.17 12.03 12.17 29.48v515.76h419.76q17.45 0 29.48 11.96 12.02 11.97 12.02 29.33t-12.02 29.54q-12.03 12.17-29.48 12.17H213.37Zm155-238v-474.26 474.26Z\">\u003C/path>\u003C/svg>\u003Csvg viewBox=\"0 -960 960 960\" xmlns=\"http://www.w3.org/2000/svg\" class=\"copy-btn-icon success-icon\">\u003Cpath d=\"m389-377.13 294.7-294.7q12.58-12.67 29.52-12.67 16.93 0 29.61 12.67 12.67 12.68 12.67 29.53 0 16.86-12.28 29.14L419.07-288.41q-12.59 12.67-29.52 12.67-16.94 0-29.62-12.67L217.41-430.93q-12.67-12.68-12.79-29.45-.12-16.77 12.55-29.45 12.68-12.67 29.62-12.67 16.93 0 29.28 12.67L389-377.13Z\">\u003C/path>\u003C/svg>\u003C/div>\u003C/button>\u003C/pre>\u003C/figure>\u003C/div>\u003C/section>\u003Csection>\u003Ch3 id=\"26-更多参考\">2.6 更多参考\u003Ca class=\"anchor\" href=\"#26-更多参考\">\u003Cspan class=\"anchor-icon\" data-pagefind-ignore=\"\">#\u003C/span>\u003C/a>\u003C/h3>\u003Cp>以下页面提供了详尽的 Slurm 使用指南，如有需要强烈建议阅读：\u003C/p>\u003Cul>\n\u003Cli>\n\u003Cp>上海交通大学超算平台: \u003Ca href=\"https://docs.hpc.sjtu.edu.cn/job/slurm.html\">Slurm 作业调度系统¶\u003C/a>\u003C/p>\n\u003C/li>\n\u003Cli>\n\u003Cp>Slurm Worker Manager: \u003Ca href=\"https://slurm.schedmd.com/documentation.html\">Slurm Documentation\u003C/a>\u003C/p>\n\u003C/li>\n\u003Cli>\n\u003Cp>CLab Server Docs: \u003Ca href=\"https://clab-hkust-gz.github.io/server-docs/userguide/lmod.html\">LMod 使用指南\u003C/a>\u003C/p>\n\u003C/li>\n\u003Cli>\n\u003Cp>LMod: \u003Ca href=\"https://lmod.readthedocs.io/en/latest/010_user.html\">User Guide for Lmod\u003C/a>\u003C/p>\n\u003C/li>\n\u003C/ul>\u003Chr>\u003C/section>\u003C/section>\u003Csection>\u003Ch2 id=\"3-任务后台查看\">3. 任务后台查看\u003Ca class=\"anchor\" href=\"#3-任务后台查看\">\u003Cspan class=\"anchor-icon\" data-pagefind-ignore=\"\">#\u003C/span>\u003C/a>\u003C/h2>\u003Cp>我们有个非常漂亮的后台，以下是它的使用教程\u003C/p>\u003Csection>\u003Ch3 id=\"31-访问-dashboard\">3.1 访问 Dashboard\u003Ca class=\"anchor\" href=\"#31-访问-dashboard\">\u003Cspan class=\"anchor-icon\" data-pagefind-ignore=\"\">#\u003C/span>\u003C/a>\u003C/h3>\u003Cp>打开浏览器访问 \u003Ca href=\"https://slurm-dashboard.ai4qc.icu/\">https://slurm-dashboard.ai4qc.icu/\u003C/a>。\u003Cbr>\n若浏览器会话中无有效的 Access Token，系统将自动重定向至 Cloudflare 零信任网关重新登录。认证成功后，将跳转至 Dashboard, 即可查看作业状态、资源使用情况等。\u003C/p>\u003Cp>更详细的使用说明，请阅读\u003Ca href=\"https://docs.rackslab.io/slurm-web/overview/overview.html\">Slurm-web/Overview\u003C/a>\n\u003Cimg width=\"1512\" height=\"867\" alt=\"image\" src=\"/posts/usingSlurm/slurm-web.png\">\u003C/p>\u003Chr>\u003C/section>\u003C/section>\u003Csection>\u003Ch2 id=\"4-密码管理\">4. 密码管理\u003Ca class=\"anchor\" href=\"#4-密码管理\">\u003Cspan class=\"anchor-icon\" data-pagefind-ignore=\"\">#\u003C/span>\u003C/a>\u003C/h2>\u003Cp>\u003Cdel>以防你忘记密码了，虽然说这东西没啥用\u003C/del>\u003C/p>\u003Csection>\u003Ch3 id=\"41-登录-profile-页面\">4.1 登录 profile 页面\u003Ca class=\"anchor\" href=\"#41-登录-profile-页面\">\u003Cspan class=\"anchor-icon\" data-pagefind-ignore=\"\">#\u003C/span>\u003C/a>\u003C/h3>\u003Cp>访问 \u003Ca href=\"https://profile.ai4qc.icu/\">https://profile.ai4qc.icu/\u003C/a> 并使用 GitHub OAuth 登录。\u003C/p>\u003C/section>\u003Csection>\u003Ch3 id=\"42-修改密码\">4.2 修改密码\u003Ca class=\"anchor\" href=\"#42-修改密码\">\u003Cspan class=\"anchor-icon\" data-pagefind-ignore=\"\">#\u003C/span>\u003C/a>\u003C/h3>\u003Cp>在 \u003Cstrong>“修改帐户密码”\u003C/strong> 区域，您可以通过以下两种方式验证身份：\u003C/p>\u003Cul>\n\u003Cli>\u003Cstrong>原密码\u003C/strong>：输入当前密码。\u003C/li>\n\u003Cli>\u003Cstrong>OAuth\u003C/strong>：使用 GitHub 快速验证（推荐，邮箱验证暂不可用）。\u003C/li>\n\u003C/ul>\u003Cp>验证通过后，在右侧输入新密码两次，确保一致，点击 \u003Cstrong>提交\u003C/strong> 即可。\u003C/p>\u003C/section>\u003Csection>\u003Ch3 id=\"43-注意事项\">4.3 注意事项\u003Ca class=\"anchor\" href=\"#43-注意事项\">\u003Cspan class=\"anchor-icon\" data-pagefind-ignore=\"\">#\u003C/span>\u003C/a>\u003C/h3>\u003Cul>\n\u003Cli>密码修改成功后，您会被强制登出，后续访问需使用新密码重新登录。\u003C/li>\n\u003Cli>请妥善保管密码，避免泄露。\u003C/li>\n\u003C/ul>\u003Chr>\u003Cp>如有任何问题，请联系系统管理员。\u003C/p>\u003C/section>\u003C/section>\u003C/section>",{"headings":51,"localImagePaths":136,"remoteImagePaths":137,"frontmatter":138,"imagePaths":144},[52,55,59,62,66,69,72,75,79,82,85,88,91,94,97,100,103,106,109,112,115,118,121,124,127,130,133],{"depth":22,"slug":53,"text":54},"slurm集群使用指南","Slurm集群使用指南#",{"depth":56,"slug":57,"text":58},2,"0-系统架构","0. 系统架构#",{"depth":56,"slug":60,"text":61},"1-环境与基本配置","1. 环境与基本配置#",{"depth":63,"slug":64,"text":65},3,"11-登录零信任平台","1.1 登录零信任平台#",{"depth":63,"slug":67,"text":68},"12-访问用户管理界面","1.2 访问用户管理界面#",{"depth":63,"slug":70,"text":71},"13-首次登录与初始密码","1.3 首次登录与初始密码#",{"depth":63,"slug":73,"text":74},"14-获取-ssh-证书","1.4 获取 SSH 证书#",{"depth":76,"slug":77,"text":78},4,"140-注意事项","1.4.0 注意事项#",{"depth":76,"slug":80,"text":81},"141-使用命令行直接登录","1.4.1 使用命令行直接登录#",{"depth":76,"slug":83,"text":84},"142-配置-ssh-config","1.4.2 配置 SSH config#",{"depth":76,"slug":86,"text":87},"143-在-vs-code-中使用","1.4.3 在 VS Code 中使用#",{"depth":76,"slug":89,"text":90},"144-在-termius-中使用","1.4.4 在 Termius 中使用#",{"depth":63,"slug":92,"text":93},"15-配置终端可选","1.5 配置终端（可选）#",{"depth":63,"slug":95,"text":96},"16-连接集群","1.6 连接集群#",{"depth":56,"slug":98,"text":99},"2-slurm-作业调度系统使用","2. Slurm 作业调度系统使用#",{"depth":63,"slug":101,"text":102},"21-分区说明","2.1 分区说明#",{"depth":63,"slug":104,"text":105},"22-登入登陆节点","2.2 登入登陆节点#",{"depth":63,"slug":107,"text":108},"23-查看集群信息","2.3 查看集群信息#",{"depth":63,"slug":110,"text":111},"24-提交作业示例","2.4 提交作业示例#",{"depth":63,"slug":113,"text":114},"25-注意事项","2.5 注意事项#",{"depth":63,"slug":116,"text":117},"26-更多参考","2.6 更多参考#",{"depth":56,"slug":119,"text":120},"3-任务后台查看","3. 任务后台查看#",{"depth":63,"slug":122,"text":123},"31-访问-dashboard","3.1 访问 Dashboard#",{"depth":56,"slug":125,"text":126},"4-密码管理","4. 密码管理#",{"depth":63,"slug":128,"text":129},"41-登录-profile-页面","4.1 登录 profile 页面#",{"depth":63,"slug":131,"text":132},"42-修改密码","4.2 修改密码#",{"depth":63,"slug":134,"text":135},"43-注意事项","4.3 注意事项#",[],[],{"title":36,"published":139,"description":39,"tags":140,"category":44,"draft":38,"minutes":141,"words":142,"excerpt":143},["Date","2026-03-01T00:00:00.000Z"],[42,43],9,1839,"欢迎使用本集群。本文档将引导您完成从环境配置到作业提交的完整流程，帮助您高效利用计算资源。",[],"usingSlurm/usingSlurm.md"]